<?xml version="1.0" encoding="UTF-8"?>
<objects serializationModel="Studio.02.02.00">
	<object class="AudioFile" id="{fe268063-566b-47cb-a35e-1e21d92e4a38}">
		<property name="assetPath">
			<value>zapsplat_household_keys_bunch_car_keys_pick_up_from_wooden_table_004_76280.mp3</value>
		</property>
		<property name="frequencyInKHz">
			<value>48</value>
		</property>
		<property name="channelCount">
			<value>1</value>
		</property>
		<property name="length">
			<value>0.81599999999999995</value>
		</property>
		<relationship name="masterAssetFolder">
			<destination>{5d08c513-1dd8-4eff-9b45-e2603913a566}</destination>
		</relationship>
	</object>
</objects>
